__init__.py
kpi_library/__init__.py
kpi_library/custom_metric.py
kpi_library/model.py
kpi_library/result_types.py
kpi_library/bi_analysis/__init__.py
kpi_library/bi_analysis/conditional_frequency_distribution.py
kpi_library/bi_analysis/correlation.py
kpi_library/categorical/__init__.py
kpi_library/categorical/frequency_distribution.py
kpi_library/categorical/frequency_distribution_percent.py
kpi_library/categorical/length_distribution.py
kpi_library/categorical/length_distribution_percent.py
kpi_library/categorical/mode.py
kpi_library/categorical/mode_frequency.py
kpi_library/categorical/mode_frequency_percent.py
kpi_library/categorical/outliers.py
kpi_library/categorical/outliers_percent.py
kpi_library/date/__init__.py
kpi_library/date/date_histogram.py
kpi_library/date/fifth_percentile.py
kpi_library/date/first_quartile.py
kpi_library/date/frequency_distribution.py
kpi_library/date/frequency_distribution_percent.py
kpi_library/date/histogram.py
kpi_library/date/histogram_percent.py
kpi_library/date/iqr.py
kpi_library/date/max.py
kpi_library/date/mean.py
kpi_library/date/median.py
kpi_library/date/min.py
kpi_library/date/mode.py
kpi_library/date/mode_frequency.py
kpi_library/date/mode_frequency_percent.py
kpi_library/date/ninety_fifth_percentile.py
kpi_library/date/number_non_transformed_dates.py
kpi_library/date/range.py
kpi_library/date/std.py
kpi_library/date/third_quartile.py
kpi_library/errors/__init__.py
kpi_library/errors/errors_class.py
kpi_library/general/__init__.py
kpi_library/general/completeness.py
kpi_library/general/completeness_percent.py
kpi_library/general/count.py
kpi_library/general/data_types.py
kpi_library/general/duplicated_entries.py
kpi_library/general/duplicated_entries_percent.py
kpi_library/general/memory_usage_bytes.py
kpi_library/general/num_columns.py
kpi_library/general/num_rows.py
kpi_library/general/position.py
kpi_library/general/unique_entries.py
kpi_library/general/unique_entries_percent.py
kpi_library/numeric/__init__.py
kpi_library-0.0.2.dist-info/METADATA
kpi_library-0.0.2.dist-info/WHEEL
kpi_library-0.0.2.dist-info/top_level.txt
kpi_library-0.0.2.dist-info/RECORD
