Metadata-Version: 2.1
Name: kpi_library
Version: 0.0.2
Summary: Quality profiler library
Author-email: Arantzazu Lopez-Larrainzar Salazar <alopezlarrainzar@iti.es>
Classifier: Programming Language :: Python :: 3
Classifier: Operating System :: OS Independent
Requires-Python: >=3.10
Requires-Dist: pandas==2.0.3
Requires-Dist: visions[type_geometry,type_image_path]~=0.7.6
Requires-Dist: nltk==3.8.1
Requires-Dist: scipy~=1.9.3
Requires-Dist: numpy~=1.23.3
Requires-Dist: regex==2022.10.31
Requires-Dist: contractions==0.1.73
Requires-Dist: pyspellchecker==0.7.1
Requires-Dist: statsmodels==0.13.5
